[
  {
    "question": "大学里选课需要注意什么？",
    "answer": "选课时要注意课程的先修要求、时间安排是否冲突、授课老师的评价以及课程的学分要求。"
  },
  {
    "question": "如何适应大学生活？",
    "answer": "适应大学生活可以从建立规律的作息时间、积极参与社团活动、主动学习和管理时间开始。"
  },
  {
    "question": "大学挂科了怎么办？",
    "answer": "如果挂科了，可以申请补考或重修，同时要分析原因，改进学习方法。"
  },
  {
    "question": "如何提高学习效率？",
    "answer": "提高学习效率可以通过制定学习计划、减少干扰、使用时间管理工具以及找到适合自己的学习方法。"
  },
  {
    "question": "大学里如何处理人际关系？",
    "answer": "处理人际关系需要尊重他人、学会倾听、保持沟通、避免无谓的争执，并建立健康的边界。"
  },
  {
    "question": "大一新生如何规划大学四年？",
    "answer": "可以分阶段规划：大一打基础、大二提升专业能力、大三实习或参加项目、大四准备就业或考研。"
  },
  {
    "question": "大学里如何找到自己的兴趣方向？",
    "answer": "可以通过选修不同课程、参加社团活动、实习和与学长学姐交流来探索兴趣方向。"
  },
  {
    "question": "如何应对大学里的压力？",
    "answer": "压力可以通过运动、冥想、与朋友倾诉、寻求心理咨询以及合理安排时间来缓解。"
  },
  {
    "question": "大学里如何提高英语水平？",
    "answer": "可以多听英语新闻、看英文电影、参加英语角、背单词以及定期做英语练习题。"
  },
  {
    "question": "大学里如何选择实习机会？",
    "answer": "可以根据专业方向、职业兴趣、实习单位的声誉以及实习内容来选择合适的实习机会。"
  },
  {
    "question": "如何避免大学期间的拖延症？",
    "answer": "可以设定明确的目标、使用番茄工作法、分解任务、制定每日计划并保持自律。"
  },
  {
    "question": "大学里如何平衡学习和娱乐？",
    "answer": "可以通过制定时间表、设定优先级、合理安排休息时间以及培养高效学习习惯来平衡两者。"
  },
  {
    "question": "大学里如何申请奖学金？",
    "answer": "奖学金通常需要提交申请表、成绩单、个人陈述以及相关证明材料，具体流程可咨询学校相关部门。"
  },
  {
    "question": "大学里如何找到合适的导师？",
    "answer": "可以通过选修老师的课程、参加学术活动、主动沟通交流以及了解导师研究方向来寻找合适的导师。"
  },
  {
    "question": "大学里如何提高自己的领导力？",
    "answer": "可以通过担任学生干部、组织活动、参与团队合作以及主动承担责任来提升领导力。"
  },
  {
    "question": "大学里如何应对考试焦虑？",
    "answer": "可以通过充分准备、模拟考试、调整心态、进行放松训练以及寻求心理支持来缓解考试焦虑。"
  },
  {
    "question": "大学里如何建立良好的学习习惯？",
    "answer": "可以从每天固定学习时间、制定学习计划、减少干扰、复习巩固知识以及定期总结反思做起。"
  },
  {
    "question": "大学里如何处理与室友的矛盾？",
    "answer": "可以通过沟通交流、尊重彼此生活习惯、制定共同规则以及必要时寻求辅导员帮助来解决矛盾。"
  },
  {
    "question": "大学里如何利用假期提升自己？",
    "answer": "可以参加实习、学习新技能、阅读书籍、旅行开阔视野或参加志愿者活动来充实假期。"
  },
  {
    "question": "大学里如何选择辅修专业？",
    "answer": "可以根据兴趣、职业规划、时间安排以及主修专业的课程负担来决定是否选择辅修专业。"
  },
  {
    "question": "大学里如何提高写作能力？",
    "answer": "可以通过多读优秀作品、练习写作、接受反馈、学习写作技巧以及参加写作课程来提升写作能力。"
  },
  {
    "question": "大学里如何准备考研？",
    "answer": "可以从大三开始规划，明确目标院校和专业、制定复习计划、收集资料、参加辅导班并保持良好的学习习惯。"
  },
  {
    "question": "大学里如何应对就业压力？",
    "answer": "可以通过实习积累经验、提升专业技能、完善简历、参加招聘会以及寻求职业咨询来缓解就业压力。"
  },
  {
    "question": "大学里如何处理失恋问题？",
    "answer": "可以接受情绪、与朋友倾诉、专注于自我成长、培养兴趣爱好以及必要时寻求心理辅导。"
  },
  {
    "question": "大学里如何建立良好的师生关系？",
    "answer": "可以通过认真听课、积极参与课堂讨论、主动请教问题以及尊重老师来建立良好的师生关系。"
  },
  {
    "question": "大学里如何提高自己的沟通能力？",
    "answer": "可以通过参加演讲、辩论、小组讨论、社交活动以及练习倾听和表达来提升沟通能力。"
  },
  {
    "question": "大学里如何处理学业与社团活动的冲突？",
    "answer": "可以通过合理安排时间、优先处理重要任务、学会取舍以及与社团成员沟通协调来解决冲突。"
  },
  {
    "question": "大学里如何选择适合自己的专业？",
    "answer": "可以根据兴趣、职业规划、课程内容、就业前景以及与学长学姐交流来选择专业。"
  },
  {
    "question": "大学里如何提升自己的创新能力？",
    "answer": "可以通过参加创新项目、竞赛、科研活动、头脑风暴以及学习跨学科知识来提升创新能力。"
  },
  {
    "question": "大学里如何处理经济压力？",
    "answer": "可以通过申请助学金、兼职工作、合理消费、制定预算以及寻求家庭支持来缓解经济压力。"
  },
  {
    "question": "大学里如何提高自己的团队合作能力？",
    "answer": "可以通过参与小组项目、社团活动、体育比赛以及主动承担团队任务来提升团队合作能力。"
  },
  {
    "question": "大学里如何准备面试？",
    "answer": "可以通过了解公司背景、准备常见问题、模拟面试、着装得体以及保持自信来准备面试。"
  },
  {
    "question": "大学里如何处理学习上的挫败感？",
    "answer": "可以通过分析失败原因、调整学习方法、设定小目标、寻求帮助以及保持积极心态来应对挫败感。"
  },
  {
    "question": "大学里如何提高自己的批判性思维能力？",
    "answer": "可以通过阅读、写作、辩论、分析案例以及质疑和反思来提升批判性思维能力。"
  },
  {
    "question": "大学里如何应对网络依赖问题？",
    "answer": "可以通过设定使用时间、培养其他兴趣爱好、与朋友面对面交流以及进行自我监督来减少网络依赖。"
  },
  {
    "question": "大学里如何提高自己的时间管理能力？",
    "answer": "可以通过制定计划、设置优先级、使用时间管理工具、记录时间消耗以及定期复盘来提升时间管理能力。"
  },
  {
    "question": "大学里如何建立自己的人脉圈？",
    "answer": "可以通过参加社团、活动、实习、讲座以及主动与他人交流来建立人脉圈。"
  },
  {
    "question": "大学里如何处理与父母的代沟问题？",
    "answer": "可以通过耐心沟通、理解父母的立场、分享自己的想法以及寻求共同话题来缓解代沟问题。"
  },
  {
    "question": "大学里如何提高自己的逻辑思维能力？",
    "answer": "可以通过学习逻辑学、做逻辑题、分析案例、阅读哲学书籍以及进行批判性思考来提升逻辑思维能力。"
  },
  {
    "question": "大学里如何处理与朋友的矛盾？",
    "answer": "可以通过坦诚沟通、换位思考、保持宽容以及必要时寻求第三方调解来解决矛盾。"
  },
  {
    "question": "大学里如何提高自己的抗压能力？",
    "answer": "可以通过锻炼身体、保持积极心态、学会放松技巧、面对挑战以及寻求心理支持来提升抗压能力。"
  },
  {
    "question": "大学里如何处理学习与恋爱的平衡？",
    "answer": "可以通过合理安排时间、与伴侣沟通、设定共同目标以及保持独立性来平衡学习与恋爱。"
  },
  {
    "question": "大学里如何选择合适的课外书籍？",
    "answer": "可以根据兴趣、专业需求、老师推荐、同学推荐以及阅读榜单来选择适合自己的课外书籍。"
  },
  {
    "question": "大学里如何提高自己的演讲能力？",
    "answer": "可以通过练习演讲、观看优秀演讲视频、参加演讲比赛、接受反馈以及学习演讲技巧来提升演讲能力。"
  },
  {
    "question": "大学里如何处理学业与兼职的冲突？",
    "answer": "可以通过合理安排时间、优先处理学业任务、选择与专业相关的兼职以及与雇主沟通协调来解决冲突。"
  },
  {
    "question": "大学里如何提升自己的跨文化沟通能力？",
    "answer": "可以通过学习外语、参加国际交流项目、与留学生交流、了解不同文化背景以及参加跨文化活动来提升跨文化沟通能力。"
  },
  {
    "question": "大学里如何处理与导师的沟通问题？",
    "answer": "可以通过提前准备问题、礼貌提问、认真听取建议以及定期反馈进展来改善与导师的沟通。"
  },
  {
    "question": "大学里如何提高自己的数据分析能力？",
    "answer": "可以通过学习统计学、编程语言（如Python、R）、使用数据分析工具（如Excel、SPSS）以及参与实际项目来提升数据分析能力。"
  },
  {
    "question": "大学里如何处理与同学的竞争关系？",
    "answer": "可以通过保持积极心态、专注于自我提升、与同学合作学习、互相帮助以及避免恶性竞争来处理竞争关系。"
  },
  {
    "question": "大学里如何提高自己的编程能力？",
    "answer": "可以通过学习编程语言、做项目、参加编程比赛、阅读技术文档以及向有经验的人请教来提升编程能力。"
  },
  {
    "question": "大学里如何处理与舍友的作息差异？",
    "answer": "可以通过沟通协商、制定作息规则、使用耳塞或眼罩、调整自己的作息时间来减少影响。"
  },
  {
    "question": "大学里如何提高自己的领导能力？",
    "answer": "可以通过担任学生干部、组织活动、带领团队完成任务以及学习领导理论来提升领导能力。"
  },
  {
    "question": "大学里如何处理与父母的沟通问题？",
    "answer": "可以通过定期沟通、表达自己的想法、理解父母的关心、避免情绪化表达以及寻求共同话题来改善沟通。"
  },
  {
    "question": "大学里如何提高自己的写作能力？",
    "answer": "可以通过多读优秀作品、练习写作、接受反馈、学习写作技巧以及参加写作课程来提升写作能力。"
  },
  {
    "question": "大学里如何应对考试焦虑？",
    "answer": "可以通过充分准备、模拟考试、调整心态、进行放松训练以及寻求心理支持来缓解考试焦虑。"
  },
  {
    "question": "大学里如何建立良好的学习习惯？",
    "answer": "可以从每天固定学习时间、制定学习计划、减少干扰、复习巩固知识以及定期总结反思做起。"
  },
  {
    "question": "大学里如何处理与室友的矛盾？",
    "answer": "可以通过沟通交流、尊重彼此生活习惯、制定共同规则以及必要时寻求辅导员帮助来解决矛盾。"
  },
  {
    "question": "大学里如何选择辅修专业？",
    "answer": "可以根据兴趣、职业规划、时间安排以及主修专业的课程负担来决定是否选择辅修专业。"
  },
  {
    "question": "大学里如何提高写作能力？",
    "answer": "可以通过多读优秀作品、练习写作、接受反馈、学习写作技巧以及参加写作课程来提升写作能力。"
  },
  {
    "question": "大学里如何准备考研？",
    "answer": "可以从大三开始规划，明确目标院校和专业、制定复习计划、收集资料、参加辅导班并保持良好的学习习惯。"
  },
  {
    "question": "大学里如何应对就业压力？",
    "answer": "可以通过实习积累经验、提升专业技能、完善简历、参加招聘会以及寻求职业咨询来缓解就业压力。"
  },
  {
    "question": "大学里如何处理失恋问题？",
    "answer": "可以接受情绪、与朋友倾诉、专注于自我成长、培养兴趣爱好以及必要时寻求心理辅导。"
  },
  {
    "question": "大学里如何建立良好的师生关系？",
    "answer": "可以通过认真听课、积极参与课堂讨论、主动请教问题以及尊重老师来建立良好的师生关系。"
  },
  {
    "question": "大学里如何提高自己的沟通能力？",
    "answer": "可以通过参加演讲、辩论、小组讨论、社交活动以及练习倾听和表达来提升沟通能力。"
  },
  {
    "question": "大学里如何处理学业与社团活动的冲突？",
    "answer": "可以通过合理安排时间、优先处理重要任务、学会取舍以及与社团成员沟通协调来解决冲突。"
  },
  {
    "question": "大学里如何选择适合自己的专业？",
    "answer": "可以根据兴趣、职业规划、课程内容、就业前景以及与学长学姐交流来选择专业。"
  },
  {
    "question": "大学里如何提升自己的创新能力？",
    "answer": "可以通过参加创新项目、竞赛、科研活动、头脑风暴以及学习跨学科知识来提升创新能力。"
  },
  {
    "question": "大学里如何处理经济压力？",
    "answer": "可以通过申请助学金、兼职工作、合理消费、制定预算以及寻求家庭支持来缓解经济压力。"
  },
  {
    "question": "大学里如何提高自己的团队合作能力？",
    "answer": "可以通过参与小组项目、社团活动、体育比赛以及主动承担团队任务来提升团队合作能力。"
  },
  {
    "question": "大学里如何准备面试？",
    "answer": "可以通过了解公司背景、准备常见问题、模拟面试、着装得体以及保持自信来准备面试。"
  },
  {
    "question": "大学里如何处理学习上的挫败感？",
    "answer": "可以通过分析失败原因、调整学习方法、设定小目标、寻求帮助以及保持积极心态来应对挫败感。"
  },
  {
    "question": "大学里如何提高自己的批判性思维能力？",
    "answer": "可以通过阅读、写作、辩论、分析案例以及质疑和反思来提升批判性思维能力。"
  },
  {
    "question": "大学里如何应对网络依赖问题？",
    "answer": "可以通过设定使用时间、培养其他兴趣爱好、与朋友面对面交流以及进行自我监督来减少网络依赖。"
  },
  {
    "question": "大学里如何提高自己的时间管理能力？",
    "answer": "可以通过制定计划、设置优先级、使用时间管理工具、记录时间消耗以及定期复盘来提升时间管理能力。"
  },
  {
    "question": "大学里如何建立自己的人脉圈？",
    "answer": "可以通过参加社团、活动、实习、讲座以及主动与他人交流来建立人脉圈。"
  },
  {
    "question": "大学里如何处理与父母的代沟问题？",
    "answer": "可以通过耐心沟通、理解父母的立场、分享自己的想法以及寻求共同话题来缓解代沟问题。"
  },
  {
    "question": "大学里如何提高自己的逻辑思维能力？",
    "answer": "可以通过学习逻辑学、做逻辑题、分析案例、阅读哲学书籍以及进行批判性思考来提升逻辑思维能力。"
  },
  {
    "question": "大学里如何处理与朋友的矛盾？",
    "answer": "可以通过坦诚沟通、换位思考、保持宽容以及必要时寻求第三方调解来解决矛盾。"
  },
  {
    "question": "大学里如何提高自己的抗压能力？",
    "answer": "可以通过锻炼身体、保持积极心态、学会放松技巧、面对挑战以及寻求心理支持来提升抗压能力。"
  },
  {
    "question": "大学里如何处理学习与恋爱的平衡？",
    "answer": "可以通过合理安排时间、与伴侣沟通、设定共同目标以及保持独立性来平衡学习与恋爱。"
  },
  {
    "question": "大学里如何选择合适的课外书籍？",
    "answer": "可以根据兴趣、专业需求、老师推荐、同学推荐以及阅读榜单来选择适合自己的课外书籍。"
  },
  {
    "question": "大学里如何提高自己的演讲能力？",
    "answer": "可以通过练习演讲、观看优秀演讲视频、参加演讲比赛、接受反馈以及学习演讲技巧来提升演讲能力。"
  },
  {
    "question": "大学里如何处理学业与兼职的冲突？",
    "answer": "可以通过合理安排时间、优先处理学业任务、选择与专业相关的兼职以及与雇主沟通协调来解决冲突。"
  },
  {
    "question": "大学里如何提升自己的跨文化沟通能力？",
    "answer": "可以通过学习外语、参加国际交流项目、与留学生交流、了解不同文化背景以及参加跨文化活动来提升跨文化沟通能力。"
  },
  {
    "question": "大学里如何处理与导师的沟通问题？",
    "answer": "可以通过提前准备问题、礼貌提问、认真听取建议以及定期反馈进展来改善与导师的沟通。"
  },
  {
    "question": "大学里如何提高自己的数据分析能力？",
    "answer": "可以通过学习统计学、编程语言（如Python、R）、使用数据分析工具（如Excel、SPSS）以及参与实际项目来提升数据分析能力。"
  },
  {
    "question": "大学里如何处理与同学的竞争关系？",
    "answer": "可以通过保持积极心态、专注于自我提升、与同学合作学习、互相帮助以及避免恶性竞争来处理竞争关系。"
  },
  {
    "question": "大学里如何提高自己的编程能力？",
    "answer": "可以通过学习编程语言、做项目、参加编程比赛、阅读技术文档以及向有经验的人请教来提升编程能力。"
  },
  {
    "question": "大学里如何处理与舍友的作息差异？",
    "answer": "可以通过沟通协商、制定作息规则、使用耳塞或眼罩、调整自己的作息时间来减少影响。"
  },
  {
    "question": "大学里如何提高自己的领导能力？",
    "answer": "可以通过担任学生干部、组织活动、带领团队完成任务以及学习领导理论来提升领导能力。"
  },
  {
    "question": "大学里如何处理与父母的沟通问题？",
    "answer": "可以通过定期沟通、表达自己的想法、理解父母的关心、避免情绪化表达以及寻求共同话题来改善沟通。"
  }
]